app/__init__.py
app/domain/__init__.py
app/domain/entity1_entity.py
app/domain/entity1_exceptions.py
app/domain/entity1_schemas.py
ddd/__init__.py
ddd/management/__init__.py
ddd/management/cli.py
ddd/management/version.py
ddd/management/commands/__init__.py
ddd/management/commands/create_dto.py
ddd/management/commands/create_entity.py
ddd/management/commands/create_repository.py
ddd/management/commands/create_serializer.py
ddd/management/commands/create_service.py
ddd/management/commands/create_view.py
ddd/management/commands/create_view_api_apiview.py
ddd/management/commands/create_view_api_viewset.py
ddd/management/commands/utils.py
ddd/management/templates/api/apiview_views.py
ddd/management/templates/api/viewset_views.py
ddd/management/templates/dto/class_dataclass.py
ddd/management/templates/dto/class_pydantic.py
ddd/management/templates/dto/imports_dataclass.py
ddd/management/templates/dto/imports_pydantic.py
ddd/management/templates/entity/class_dataclass.py
ddd/management/templates/entity/class_pydantic.py
ddd/management/templates/entity/exceptions.py
ddd/management/templates/entity/imports_dataclass.py
ddd/management/templates/entity/imports_pydantic.py
ddd/management/templates/entity/schemas_dataclass.py
ddd/management/templates/entity/schemas_pydantic.py
ddd/management/templates/repository/class.py
ddd/management/templates/repository/exceptions.py
ddd/management/templates/repository/mappers_dataclass.py
ddd/management/templates/repository/mappers_pydantic.py
ddd/management/templates/routers/api_apiview_urls.py
ddd/management/templates/routers/api_viewset_urls.py
ddd/management/templates/routers/web_urls.py
ddd/management/templates/serializer/class.py
ddd/management/templates/serializer/imports.py
ddd/management/templates/services/class.py
ddd/management/templates/services/imports.py
ddd/management/templates/services/old/function_crud.py
ddd/management/templates/templates/_web_form_errors.html
ddd/management/templates/templates/_web_global_errors.html
ddd_cli-1.9.18.dist-info/METADATA
ddd_cli-1.9.18.dist-info/WHEEL
ddd_cli-1.9.18.dist-info/entry_points.txt
ddd_cli-1.9.18.dist-info/top_level.txt
ddd_cli-1.9.18.dist-info/RECORD
