Metadata-Version: 2.2
Name: ddd-cli
Version: 1.9.18
Summary: CLI for adding DDD support to Python/Django projects
Author: Ragnar Bermúdez La O
Author-email: ragnarbermudezlao@gmail.com
Classifier: Programming Language :: Python :: 3
Classifier: Framework :: Django
Requires-Dist: django
Requires-Dist: jinja2
Requires-Dist: colorama
Dynamic: author
Dynamic: author-email
Dynamic: classifier
Dynamic: description
Dynamic: description-content-type
Dynamic: requires-dist
Dynamic: summary
